{
    "controller": [
        {
            "name": "安卓端",
            "type": "Adb"
        }
    ],
    "resource": [
        {
            "name": "台服",
            "path": [
                "{PROJECT_DIR}/resource/base"
            ]
        },
        {
            "name": "日服",
            "path": [
                "{PROJECT_DIR}/resource/jp"
            ]
        }
    ],
    "task": [
        {
            "name": "一键启动",
            "entry": "StartUp"
        },
        {
            "name": "无限池抽白金",
            "entry": "GachaPlatinum"
        },
        {
            "name": "无限池抽武器",
            "entry": "GachaArms"
        }
    ]
}